tkmats/__init__.py
tkmats/frames.py
tkmats/version.py
tkmats-0.8.0.dist-info/METADATA
tkmats-0.8.0.dist-info/WHEEL
tkmats-0.8.0.dist-info/top_level.txt
tkmats-0.8.0.dist-info/RECORD
