Metadata-Version: 2.1
Name: tkmats
Version: 0.8.0
Summary: A tkinter-based front-end GUI for trigger and monitoring hardware tests based on the MATS package
Home-page: https://github.com/slightlynybbled/tkmats
Author: Jason R. Jones
Author-email: slightlynybbled@gmail.com
License: MIT
Platform: UNKNOWN
Classifier: License :: OSI Approved :: MIT License
Classifier: Development Status :: 3 - Alpha
Classifier: Programming Language :: Python
Classifier: Programming Language :: Python :: 3
Classifier: Programming Language :: Python :: 3.6
Classifier: Programming Language :: Python :: 3.7
Classifier: Programming Language :: Python :: Implementation :: CPython
Requires-Python: >=3.6.0
Requires-Dist: mats (>=0.30.0)
